py2dmath.cpython-311-s390x-linux-gnu.so
py2dmath-1.0.0.dist-info/LICENSE
py2dmath-1.0.0.dist-info/RECORD
py2dmath-1.0.0.dist-info/WHEEL
py2dmath-1.0.0.dist-info/top_level.txt
py2dmath-1.0.0.dist-info/METADATA
